cppparallelbufferedsort/README.MD
cppparallelbufferedsort/__init__.py
cppparallelbufferedsort/cppparallelbufferedsort.dll
cppparallelbufferedsort/cppparallelbufferedsort.ini
cppparallelbufferedsort/cppparallelbufferedsortmodule.py
cppparallelbufferedsort/requirements.txt
cppparallelbufferedsort/thirdparty.json
cppparallelbufferedsort-0.10.dist-info/LICENSE.rst
cppparallelbufferedsort-0.10.dist-info/METADATA
cppparallelbufferedsort-0.10.dist-info/WHEEL
cppparallelbufferedsort-0.10.dist-info/top_level.txt
cppparallelbufferedsort-0.10.dist-info/RECORD
