Metadata-Version: 2.1
Name: cppparallelbufferedsort
Version: 0.10
Summary: parallel_buffered_sort from C++ for Python (Windows)
Home-page: https://github.com/hansalemaos/cppparallelbufferedsort
Author: Johannes Fischer
Author-email: <aulasparticularesdealemaosp@gmail.com>
License: MIT
Keywords: parallel_buffered_sort,c++,numpy,sort
Classifier: Development Status :: 4 - Beta
Classifier: Programming Language :: Python :: 3 :: Only
Classifier: Programming Language :: Python :: 3.9
Classifier: Topic :: Scientific/Engineering :: Visualization
Classifier: Topic :: Software Development :: Libraries :: Python Modules
Classifier: Topic :: Text Editors :: Text Processing
Classifier: Topic :: Text Processing :: General
Classifier: Topic :: Text Processing :: Indexing
Classifier: Topic :: Text Processing :: Filters
Classifier: Topic :: Utilities
License-File: LICENSE.rst
Requires-Dist: flexible-partial
Requires-Dist: numpy
